index_template/__init__.py
index_template/create_templates.py
index_template/field_definitions.py
index_template/index_configs.py
index_template/template_schema.py
index_template/utils.py
index_template-0.1.0.dist-info/WHEEL
index_template-0.1.0.dist-info/METADATA
index_template-0.1.0.dist-info/RECORD
