Metadata-Version: 2.1
Name: index-template
Version: 0.1.0
Summary: 
Home-page: https://github.com/MetaSearch-IO/IndexTemplate
Author: kaito-hao
Author-email: anya@kaito.ai
Requires-Python: >=3.9,<4.0
Classifier: Programming Language :: Python :: 3
Classifier: Programming Language :: Python :: 3.9
Classifier: Programming Language :: Python :: 3.10
Requires-Dist: loguru (>=0.5.0,<0.6.0)
Requires-Dist: requests (>=2.28,<3.0)
Project-URL: Repository, https://github.com/MetaSearch-IO/KaitoModelPython.git
